pyqft/__init__.py
pyqft-0.0.1.dist-info/LICENSE
pyqft-0.0.1.dist-info/METADATA
pyqft-0.0.1.dist-info/WHEEL
pyqft-0.0.1.dist-info/top_level.txt
pyqft-0.0.1.dist-info/RECORD
