Metadata-Version: 2.1
Name: pyqft
Version: 0.0.1
Summary: A python package for QFT calculations
Author: 
Author-email: A T M Ragib Raihan <atmragibraihan@gmail.com>
License: Copyright (c) 2018 The Python Packaging Authority
Project-URL: Homepage, https://test.pypi.org/project/pyqft
Keywords: QFT,Feynman,Quantum Field Theory
Classifier: License :: OSI Approved :: MIT License
Classifier: Programming Language :: Python
Classifier: Programming Language :: Python :: 3
Requires-Python: >=3.10
License-File: LICENSE
